{
  "main": {
    "id": "19ce50c2644212d5",
    "type": "split",
    "children": [
      {
        "id": "429ca614b12e2914",
        "type": "tabs",
        "children": [
          {
            "id": "16739414e37669df",
            "type": "leaf",
            "state": {
              "type": "empty",
              "state": {}
            }
          },
          {
            "id": "5d8b574a71652f1a",
            "type": "leaf",
            "state": {
              "type": "markdown",
              "state": {
                "file": "Templates/Basico.md",
                "mode": "source",
                "source": true
              }
            }
          },
          {
            "id": "7c95f870a63ea06f",
            "type": "leaf",
            "state": {
              "type": "markdown",
              "state": {
                "file": "Home.md",
                "mode": "source",
                "source": true
              }
            }
          }
        ],
        "currentTab": 2
      }
    ],
    "direction": "vertical"
  },
  "left": {
    "id": "e8637090cfdbf1c3",
    "type": "split",
    "children": [
      {
        "id": "3a5274c17e8c178b",
        "type": "tabs",
        "children": [
          {
            "id": "b0d6f9c53f87daf4",
            "type": "leaf",
            "state": {
              "type": "file-explorer",
              "state": {
                "sortOrder": "alphabetical"
              }
            }
          },
          {
            "id": "439af06bf62afa62",
            "type": "leaf",
            "state": {
              "type": "search",
              "state": {
                "query": "",
                "matchingCase": false,
                "explainSearch": false,
                "collapseAll": false,
                "extraContext": false,
                "sortOrder": "alphabetical"
              }
            }
          },
          {
            "id": "0d97d72fb3e50ad2",
            "type": "leaf",
            "state": {
              "type": "bookmarks",
              "state": {}
            }
          },
          {
            "id": "83c84b38bded2ee5",
            "type": "leaf",
            "state": {
              "type": "mk-path-view",
              "state": {}
            }
          }
        ]
      }
    ],
    "direction": "horizontal",
    "width": 300,
    "collapsed": true
  },
  "right": {
    "id": "141513e9a02dc07d",
    "type": "split",
    "children": [
      {
        "id": "2869cbde33abc6a1",
        "type": "tabs",
        "children": [
          {
            "id": "6384ae9e272ccc53",
            "type": "leaf",
            "state": {
              "type": "backlink",
              "state": {
                "collapseAll": false,
                "extraContext": false,
                "sortOrder": "alphabetical",
                "showSearch": false,
                "searchQuery": "",
                "backlinkCollapsed": false,
                "unlinkedCollapsed": true
              }
            }
          },
          {
            "id": "c3423a841f310a9b",
            "type": "leaf",
            "state": {
              "type": "outgoing-link",
              "state": {
                "linksCollapsed": false,
                "unlinkedCollapsed": true
              }
            }
          },
          {
            "id": "fbf91bf9cabd7dd4",
            "type": "leaf",
            "state": {
              "type": "tag",
              "state": {
                "sortOrder": "frequency",
                "useHierarchy": true
              }
            }
          },
          {
            "id": "f0fde6747853fbba",
            "type": "leaf",
            "state": {
              "type": "outline",
              "state": {}
            }
          },
          {
            "id": "86b25e38ac04c3f0",
            "type": "leaf",
            "state": {
              "type": "all-properties",
              "state": {
                "sortOrder": "frequency"
              }
            }
          }
        ]
      }
    ],
    "direction": "horizontal",
    "width": 300,
    "collapsed": true
  },
  "left-ribbon": {
    "hiddenItems": {
      "switcher:Abrir selector rápido": false,
      "graph:Abrir vista gráfica": false,
      "canvas:Crear nuevo canvas": false,
      "daily-notes:Abrir la nota de hoy": false,
      "templates:Insertar plantilla": false,
      "command-palette:Abrir paleta de comandos": false,
      "markdown-importer:Abrir el importador de Markdown": false,
      "table-editor-obsidian:Advanced Tables Toolbar": false,
      "obsidian-excalidraw-plugin:Create new drawing": false,
      "templater-obsidian:Templater": false,
      "homepage:Open homepage": false
    }
  },
  "active": "1931447eae6cdf62",
  "lastOpenFiles": [
    "Home.md",
    "Spaces/Home",
    "Spaces",
    "Banners/Anatomia.jpg",
    "Banners/1416538.jpg",
    "Banners/136918.jpg",
    "Banners",
    "Nueva carpeta",
    "Templates/Basico.md",
    "Scripts",
    "Templates",
    "Materias/undefined/Fisiología del Sistema Digestivo.md",
    "Materias/Farmacologia del Sistema digestivo.md",
    "Materias/undefined",
    "Materias/Fisiologia del Sistema Digestivo.md",
    "Materias/Embriología del Sistema Digestivo.md",
    "Materias/Anatomía del Sistema Digestivo.md",
    "Materias/undefinedEmbriologia de Sistema Digestivo.md",
    "Materias/Juan.md",
    "Materias/Juan.md",
    "Materias/Template.md",
    "Sin título 2.md",
    "Sin título 1.md",
    "Materias/Embriologia.md",
    "Materias/Sin título 1.md",
    "Embriologia.md",
    "Materias/Embriología.md",
    "Embriología.md",
    "Embriologia.md",
    "Embriologia1.md",
    "Materias",
    "Templates"
  ]
}